README.md
setup.py
monsdatabase/__init__.py
monsdatabase/db.py
monsdatabase.egg-info/PKG-INFO
monsdatabase.egg-info/SOURCES.txt
monsdatabase.egg-info/dependency_links.txt
monsdatabase.egg-info/top_level.txt