Metadata-Version: 2.1
Name: monsdatabase
Version: 0.1
Summary: powerfull DB for your project.
Author: grubx64
License: MIT
